<?xml version="1.0" encoding="utf-8"?>
<updates>
	<update>
		<name>Plugin AutoReadMore</name>
		<description/>
		<element>autoreadmore</element>
		<type>plugin</type>
		<folder>content</folder>		
		<version>5.1.5</version>
		<client>site</client>
		<downloads>
			<downloadurl type="full" format="zip">https://github.com/conseilgouz/AutoReadMore-J4/archive/refs/tags/5.1.5.zip</downloadurl>
		</downloads>
		<targetplatform name="joomla" version="3.10"/>
	</update>
	<update>
		<name>Plugin AutoReadMore</name>
		<description/>
		<element>autoreadmore</element>
		<type>plugin</type>
		<folder>content</folder>		
		<version>5.1.8</version>
		<client>site</client>
		<downloads>
			<downloadurl type="full" format="zip">https://github.com/conseilgouz/AutoReadMore-J4/archive/refs/tags/5.1.8.zip</downloadurl>
		</downloads>
		<changelogurl>https://raw.githubusercontent.com/conseilgouz/AutoReadMore-J4/master/plg_autoreadmore_changelog.xml</changelogurl>
		<targetplatform name="joomla" version="((4\.(0|1|2|3|4))|(5\.(0|1|2|3|4|5|6|7|8|9)))"/>
		<sha256>93c0d71b55d88baea8875f6e76c7c14d8c625d97f45396d8114151ab3673ed99</sha256>
	</update>
</updates>
